Workbook

Sheet TATA CFS
A1: In Rs. Cr. | B1: Mar'23 | C1: Mar'24 | D1: Mar'25 | E1: Mar'26
A2: Cash from Operating Activity | B2: 21683 | C2: 20301 | D2: 23138 | E2: 35064 | H2: TATA STEELS
A3: Profit Before Tax | B3: 18235 | C3: -1147 | D3: 8413 | E3: 15969
A4: Adjustments | B4: 12673 | C4: 23384 | D4: 15516 | E4: 18250
A5: OCF Before Working Capital | B5: 30908 | C5: 22237 | D5: 23929 | E5: 34219
A6: Working Capital Changes | B6: -3706 | C6: 3384 | D6: 2207 | E6: 5442
A7: Taxes Paid | B7: -5519 | C7: -5320 | D7: -2998 | E7: -4597
A8: Cash from Investing Activity | B8: -18680 | C8: -14251 | D8: -13798 | E8: -14905
A9: Net Fixed Assets Purchased | B9: -13815 | C9: -17731 | D9: -15157 | E9: -13696
A10: Fixed Assets Purchased | B10: -14142 | C10: -18207 | D10: -15671 | E10: -14559
A11: Fixed Assets Sold | B11: 328 | C11: 475 | D11: 514 | E11: 863
A12: Investment Purchased | B12: -326 | C12: -478 | D12: -1345 | E12: -1700
A13: Investment Sold | B13: 5214 | C13: 3171 | D13: 1021 | E13: 1109
A14: Interest Recieved | B14: 248 | C14: 333 | D14: 616 | E14: 650
... A17: Cash from Financing Activity | B17: -6981 | C17: -11097 | D17: -7002 | E17: -21387
A18: Proceeds From Shares | B18: 1.37 | C18: — | D18: — | E18: —
A19: Net Long Term Borrowings | B19: 12163 | C19: 1579 | D19: 7814 | E19: -11804
A20: Proceeds From Borrowings | B20: 16769 | C20: 13329 | D20: 23893 | E20: 12092
A21: Repayment From Borrowings | B21: -4606 | C21: -11751 | D21: -16079 | E21: -23897
A22: Interest Paid | B22: -6120 | C22: -8145 | D22: -8119 | E22: -8066
A23: Dividend Paid | B23: -6293 | C23: -4429 | D23: -4490 | E23: -4490
A24: Net Cash Flow | B24: -3977 | C24: -5048 | D24: 2337 | E24: -1228
A25: Opening Cash & Cash Equivalents | B25: 15607 | C25: 12130 | D25: 7081 | E25: 9605
A26: Effect of FX | B26: 500 | C26: -1.3 | D26: 187 | E26: 508
A27: Closing Cash & Cash Equivalents | B27: 12130 | C27: 7081 | D27: 9605 | E27: 8885
A28: Net Capex (est) | B28: 13815 | C28: 17731 | D28: 15157 | E28: 13696
A29: Free Cash Flow (est) | B29: 7868 | C29: 2569 | D29: 7981 | E29: 21368

Sheet TATA-Ratio Analysis
A1: TATA CASH FLOW STATEMENT ANALYSIS - KEY RATIOS
A2: Particulars | B2: Mar'23 | C2: Mar'24 | D2: Mar'25 | E2: Mar'26 | F2: Formula
A4: OCF to PBT Ratio | B4: ='TATA CFS'!B2/'TATA CFS'!B3 -> 1.1890869 | C4: ='TATA CFS'!C2/'TATA CFS'!C3 -> -17.699215 | D4: ='TATA CFS'!D2/'TATA CFS'!D3 -> 2.7502674 | E4: ='TATA CFS'!E2/'TATA CFS'!E3 -> 2.1957543 | F4: OCF ÷ PBT (From TATA CFS rows 2,3)
A5: OCF to Capex Ratio | B5: ='TATA CFS'!B2/'TATA CFS'!B28 -> 1.5695259 | C5: ='TATA CFS'!C2/'TATA CFS'!C28 -> 1.1449439 | D5: ='TATA CFS'!D2/'TATA CFS'!D28 -> 1.5265554 | E5: ='TATA CFS'!E2/'TATA CFS'!E28 -> 2.5601636 | F5: OCF ÷ Capex (From TATA CFS rows 2,28)
A6: OCF to Net Cash Flow Ratio | B6: ='TATA CFS'!B2/'TATA CFS'!B24 -> -5.4520996 | C6: ='TATA CFS'!C2/'TATA CFS'!C24 -> -4.0215927 | D6: ='TATA CFS'!D2/'TATA CFS'!D24 -> 9.9007274 | E6: ='TATA CFS'!E2/'TATA CFS'!E24 -> -28.553746 | F6: OCF ÷ Net Cash Flow (From TATA CFS rows 2,24)
A8: FCF Margin (FCF/OCF %) | B8: ='TATA CFS'!B29/'TATA CFS'!B2*100 -> 36.286492 | C8: ='TATA CFS'!C29/'TATA CFS'!C2*100 -> 12.654549 | D8: ='TATA CFS'!D29/'TATA CFS'!D2*100 -> 34.493042 | E8: ='TATA CFS'!E29/'TATA CFS'!E2*100 -> 60.939995 | F8: FCF ÷ OCF × 100 (From TATA CFS rows 29,2) %
A9: Capex as % of OCF | B9: ='TATA CFS'!B28/'TATA CFS'!B2*100 -> 63.713508 | C9: ='TATA CFS'!C28/'TATA CFS'!C2*100 -> 87.340525 | D9: ='TATA CFS'!D28/'TATA CFS'!D2*100 -> 65.506958 | E9: ='TATA CFS'!E28/'TATA CFS'!E2*100 -> 39.060005 | F9: Capex ÷ OCF × 100 (From TATA CFS rows 28,2) %
A11: OCF to Closing Cash Ratio | B11: ='TATA CFS'!B2/'TATA CFS'!B27 -> 1.7875515 | C11: ='TATA CFS'!C2/'TATA CFS'!C27 -> 2.8669679 | D11: ='TATA CFS'!D2/'TATA CFS'!D27 -> 2.4089537 | E11: ='TATA CFS'!E2/'TATA CFS'!E27 -> 3.9464266 | F11: OCF ÷ Closing Cash (From TATA CFS rows 2,27)
A13: Operating to Investing Activity Ratio | B13: ='TATA CFS'!B2/'TATA CFS'!B8 -> -1.1607602 | C13: ='TATA CFS'!C2/'TATA CFS'!C8 -> -1.4245316 | D13: ='TATA CFS'!D2/'TATA CFS'!D8 -> -1.6769097 | E13: ='TATA CFS'!E2/'TATA CFS'!E8 -> -2.3524992 | F13: OCF ÷ (Investing) - Times (From TATA CFS rows 2,8)
A14: Operating to Financing Activity Ratio | B14: ='TATA CFS'!B2/'TATA CFS'!B17 -> -3.106002 | C14: ='TATA CFS'!C2/'TATA CFS'!C17 -> -1.8294134 | D14: ='TATA CFS'!D2/'TATA CFS'!D17 -> -3.3044844 | E14: ='TATA CFS'!E2/'TATA CFS'!E17 -> -1.6395006 | F14: OCF ÷ (Financing) - (From TATA CFS rows 2,17)
A15: Dividend Paid | B15: 6293 | C15: 4429 | D15: 4490 | E15: 4490
A16: Capital Allocation Ratio (Capex+Div)/OCF | B16: =('TATA CFS'!B28+'TATA-Ratio Analysis'!B15)/'TATA CFS'!B2 -> 0.92736245 | C16: =('TATA CFS'!C28+'TATA-Ratio Analysis'!C15)/'TATA CFS'!C2 -> 1.0915718 | D16: =('TATA CFS'!D28+'TATA-Ratio Analysis'!D15)/'TATA CFS'!D2 -> 0.84912266 | E16: =('TATA CFS'!E28+'TATA-Ratio Analysis'!E15)/'TATA CFS'!E2 -> 0.51865161 | F16: (Capex + Div) ÷ OCF (From TATA CFS rows 28,2, CFS analysis row 15)

Sheet TATA Summary

Sheet JSW CFS
A1: In Rs. Cr. | B1: Mar'23 | C1: Mar'24 | D1: Mar'25 | E1: Mar'26
A2: Cash from Operating Activity | B2: 23323 | C2: 12078 | D2: 20899 | E2: 25152
A3: Profit Before Tax | B3: 5655 | C3: 13380 | D3: 5077 | E3: 29250 | H3: JSW STEELS
A4: Adjustments | B4: 15201 | C4: 15092 | D4: 18476 | E4: 2835
A5: OCF Before Working Capital | B5: 20856 | C5: 28472 | D5: 23553 | E5: 32085
A6: Working Capital Changes | B6: 3105 | C6: -13615 | D6: -681 | E6: -3708
A7: Taxes Paid | B7: -638 | C7: -2779 | D7: -1973 | E7: -3225
A8: Cash from Investing Activity | B8: -10711 | C8: -14638 | D8: -16997 | E8: 18690
A9: Net Fixed Assets Purchased | B9: -14637 | C9: -15547 | D9: -12635 | E9: -14542
A10: Fixed Assets Purchased | B10: -14784 | C10: -15801 | D10: -12694 | E10: -14654
A11: Fixed Assets Sold | B11: 147 | C11: 254 | D11: 59 | E11: 112
A12: Investment Purchased | B12: -445 | C12: -3980 | D12: -14007 | E12: —
A13: Investment Sold | B13: 3290 | C13: 4599 | D13: 8911 | E13: —
A14: Interest Recieved | B14: 600 | C14: 899 | D14: 660 | E14: 672
A15: Dividends Recieved | B15: 21 | C15: 21 | D15: 24 | E15: 24
A16: Subsidiary Investments | B16: — | C16: -630 | D16: — | E16: —
A17: Cash from Financing Activity | B17: -5977 | C17: -5005 | D17: -262 | E17: -16111
A18: Proceeds From Shares | B18: 59 | C18: 6 | D18: -44 | E18: —
A19: Net Long Term Borrowings | B19: 3792 | C19: 3563 | D19: 11546 | E19: -7296
A20: Proceeds From Borrowings | B20: 17950 | C20: 19891 | D20: 28243 | E20: 14399
A21: Repayment From Borrowings | B21: -14158 | C21: -16328 | D21: -16697 | E21: -21695
A22: Interest Paid | B22: -6902 | C22: -8087 | D22: -8835 | E22: -8922
A23: Dividend Paid | B23: -4194 | C23: -822 | D23: -1785 | E23: -685
A24: Net Cash Flow | B24: 6635 | C24: -7565 | D24: 3640 | E24: 27731
A25: Opening Cash & Cash Equivalents | B25: 8808 | C25: 15424 | D25: 8030 | E25: 11655
A26: Effect of FX | B26: — | C26: — | D26: — | E26: —
A27: Closing Cash & Cash Equivalents | B27: 15424 | C27: 8030 | D27: 11655 | E27: 39256
A28: Net Capex (est) | B28: 14637 | C28: 15547 | D28: 12635 | E28: 14542
A29: Free Cash Flow (est) | B29: 8686 | C29: -3469 | D29: 8264 | E29: 10610

Sheet JSW-Ratio Analysis
A1: JSW CASH FLOW STATEMENT ANALYSIS - KEY RATIOS
A2: Particulars | B2: Mar'23 | C2: Mar'24 | D2: Mar'25 | E2: Mar'26 | F2: Formula
A4: OCF to PBT Ratio | B4: ='JSW CFS'!B2/'JSW CFS'!B3 -> 4.1243148 | C4: ='JSW CFS'!C2/'JSW CFS'!C3 -> 0.90269058 | D4: ='JSW CFS'!D2/'JSW CFS'!D3 -> 4.1164073 | E4: ='JSW CFS'!E2/'JSW CFS'!E3 -> 0.85989744 | F4: OCF ÷ PBT (From JSW CFS rows 2,3)
A5: OCF to Capex Ratio | B5: ='JSW CFS'!B2/'JSW CFS'!B28 -> 1.5934276 | C5: ='JSW CFS'!C2/'JSW CFS'!C28 -> 0.77687014 | D5: ='JSW CFS'!D2/'JSW CFS'!D28 -> 1.6540562 | E5: ='JSW CFS'!E2/'JSW CFS'!E28 -> 1.7296108 | F5: OCF ÷ Capex (From JSW CFS rows 2,28)
A6: OCF to Net Cash Flow Ratio | B6: ='JSW CFS'!B2/'JSW CFS'!B24 -> 3.5151469 | C6: ='JSW CFS'!C2/'JSW CFS'!C24 -> -1.5965631 | D6: ='JSW CFS'!D2/'JSW CFS'!D24 -> 5.7414835 | E6: ='JSW CFS'!E2/'JSW CFS'!E24 -> 0.90699939 | F6: OCF ÷ Net Cash Flow (From JSW CFS rows 2,24)
A8: FCF Margin (FCF/OCF %) | B8: ='JSW CFS'!B29/'JSW CFS'!B2*100 -> 37.242207 | C8: ='JSW CFS'!C29/'JSW CFS'!C2*100 -> -28.721643 | D8: ='JSW CFS'!D29/'JSW CFS'!D2*100 -> 39.542562 | E8: ='JSW CFS'!E29/'JSW CFS'!E2*100 -> 42.183524 | F8: FCF ÷ OCF × 100 (From JSW CFS rows 29,2) %
A9: Capex as % of OCF | B9: ='JSW CFS'!B28/'JSW CFS'!B2*100 -> 62.757793 | C9: ='JSW CFS'!C28/'JSW CFS'!C2*100 -> 128.72164 | D9: ='JSW CFS'!D28/'JSW CFS'!D2*100 -> 60.457438 | E9: ='JSW CFS'!E28/'JSW CFS'!E2*100 -> 57.816476 | F9: Capex ÷ OCF × 100 (From JSW CFS rows 28,2) %
A11: OCF to Closing Cash Ratio | B11: ='JSW CFS'!B2/'JSW CFS'!B27 -> 1.512124 | C11: ='JSW CFS'!C2/'JSW CFS'!C27 -> 1.5041096 | D11: ='JSW CFS'!D2/'JSW CFS'!D27 -> 1.793136 | E11: ='JSW CFS'!E2/'JSW CFS'!E27 -> 0.64071734 | F11: OCF ÷ Closing Cash (From JSW CFS rows 2,27)
A13: Operating to Investing Activity Ratio | B13: ='JSW CFS'!B2/'JSW CFS'!B8 -> -2.1774811 | C13: ='JSW CFS'!C2/'JSW CFS'!C8 -> -0.82511272 | D13: ='JSW CFS'!D2/'JSW CFS'!D8 -> -1.2295699 | E13: ='JSW CFS'!E2/'JSW CFS'!E8 -> 1.3457464 | F13: OCF ÷ (Investing) - Times (From JSW CFS rows 2,8)
A14: Operating to Financing Activity Ratio | B14: ='JSW CFS'!B2/'JSW CFS'!B17 -> -3.9021248 | C14: ='JSW CFS'!C2/'JSW CFS'!C17 -> -2.4131868 | D14: ='JSW CFS'!D2/'JSW CFS'!D17 -> -79.767176 | E14: ='JSW CFS'!E2/'JSW CFS'!E17 -> -1.5611694 | F14: OCF ÷ (Financing) - (From JSW CFS rows 2,17)
A15: Dividend Paid | B15: 4194 | C15: 822 | D15: 1785 | E15: 685
A16: Capital Allocation Ratio (Capex+Div)/OCF | B16: =('JSW CFS'!B28+'JSW-Ratio Analysis'!B15)/'JSW CFS'!B2 -> 0.80740042 | C16: =('JSW CFS'!C28+'JSW-Ratio Analysis'!C15)/'JSW CFS'!C2 -> 1.3552741 | D16: =('JSW CFS'!D28+'JSW-Ratio Analysis'!D15)/'JSW CFS'!D2 -> 0.68998517 | E16: =('JSW CFS'!E28+'JSW-Ratio Analysis'!E15)/'JSW CFS'!E2 -> 0.60539917 | F16: (Capex + Div) ÷ OCF (From JSW CFS rows 28,2, CFS analysis row 15)

Sheet JSW Summary

Sheet Perfo Analysis
A1: TATA & JSW - 3-YEAR CASH FLOW PERFORMANCE ANALYSIS | I1: TATA VS JSW - COMPARATIVE CASH FLOW ANALYSIS
A3: TATA CONSOLIDATED 3-YEAR PERFORMANCE (FY 2024-26) | I3: FY 2023-24 (MAR'26) COMPARISON
A4: Particulars | B4: Mar'24 | C4: Mar'25 | D4: Mar'26 | I4: Particulars | J4: TATA | K4: JSW | L4: Difference | M4: TATA % | N4: JSW%
A5: Operating Cash Flow | B5: 20301 | C5: 23138 | D5: 35064 | I5: Operating Cash Flow (Rs. Cr.) | J5: 20301 | K5: 12078 | L5: =J5-K5 -> 8223 | M5: =J5/(J5+K5)*100 -> 62.698045 | N5: =K5/(J5+K5)*100 -> 37.301955
A6: Investing Activity | B6: -14251 | C6: -13798 | D6: -14905 | I6: Free Cash Flow (Rs. Cr.) | J6: 2569 | K6: -3469 | L6: =J6-K6 -> 6038 | M6: =(-J6/(J6+K6)*100) -> 285.44444 | N6: =(-K6/(J6+K6)) -> -3.8544444
A7: Financing Activity | B7: -11097 | C7: -7002 | D7: -21387 | I7: Capital Expenditure (Rs. Cr.) | J7: 17731 | K7: 15547 | L7: =J7-K7 -> 2184 | M7: =J7/(J7+K7)*100 -> 53.281447 | N7: =K7/(J7+K7)*100 -> 46.718553
A8: Net Cash Flow | B8: -5048 | C8: 2337 | D8: -1228 | I8: Closing Cash (Rs. Cr.) | J8: 7081 | K8: 8030 | L8: =J8-K8 -> -949 | M8: =J8/(J8+K8)*100 -> 46.859903 | N8: =K8/(J8+K8)*100 -> 53.140097
A9: Free Cash Flow | B9: 2569 | C9: 7981 | D9: 21368 | I9: OCF to Capex Ratio (Times) | J9: =J5/J7 -> 1.1449439 | K9: =K5/K7 -> 0.77687014 | L9: =J9-K9 -> 0.36807375
A10: Capital Expenditure | B10: 17731 | C10: 15157 | D10: 13696
A11: Closing Cash | B11: 7081 | C11: 9605 | D11: 8885 | I11: FY 2024-25 (MAR'25) COMPARISON
I12: Particulars | J12: TATA | K12: JSW | L12: Difference | M12: TATA % | N12: JSW%
I13: Operating Cash Flow (Rs. Cr.) | J13: 23138 | K13: 20899 | L13: =J13-K13 -> 2239 | M13: =J13/(J13+K13)*100 -> 52.54218 | N13: =K13/(J13+K13)*100 -> 47.45782
A14: JSW CONSOLIDATED 3-YEAR PERFORMANCE (FY 2024-26) | I14: Free Cash Flow (Rs. Cr.) | J14: 7981 | K14: 8264 | L14: =J14-K14 -> -283 | M14: =J14/(J14+K14)*100 -> 49.128963 | N14: =K14/(J14+K14)*100 -> 50.871037
A15: Particulars | B15: Mar'24 | C15: Mar'25 | D15: Mar'26 | I15: Capital Expenditure (Rs. Cr.) | J15: 15157 | K15: 12635 | L15: =J15-K15 -> 2522 | M15: =J15/(J15+K15)*100 -> 54.537277 | N15: =K15/(J15+K15)*100 -> 45.462723
A16: Operating Cash Flow | B16: 12078 | C16: 20899 | D16: 25152 | I16: Closing Cash (Rs. Cr.) | J16: 9605 | K16: 11655 | L16: =J16-K16 -> -2050 | M16: =J16/(J16+K16)*100 -> 45.178739 | N16: =K16/(J16+K16)*100 -> 54.821261
A17: Investing Activity | B17: -14638 | C17: -16997 | D17: 18690 | I17: OCF to Capex Ratio (Times) | J17: =J13/J15 -> 1.5265554 | K17: =K13/K15 -> 1.6540562 | L17: =J17-K17 -> -0.12750081
A18: Financing Activity | B18: -5005 | C18: -262 | D18: -16111
A19: Net Cash Flow | B19: -7565 | C19: 3640 | D19: 27731 | I19: FY 2025-26 (MAR'26) COMPARISON
A20: Free Cash Flow | B20: -3469 | C20: 8264 | D20: 10610 | I20: Particulars | J20: TATA | K20: JSW | L20: Difference | M20: TATA % | N20: JSW%
A21: Capital Expenditure | B21: 15547 | C21: 12635 | D21: 14542 | I21: Operating Cash Flow (Rs. Cr.) | J21: 35064 | K21: 25152 | L21: =J21-K21 -> 9912 | M21: =J21/(J21+K21)*100 -> 58.230371 | N21: =K21/(J21+K21)*100 -> 41.769629
A22: Closing Cash | B22: 8030 | C22: 11655 | D22: 39256 | I22: Free Cash Flow (Rs. Cr.) | J22: 21368 | K22: 10610 | L22: =J22-K22 -> 10758 | M22: =J22/(J22+K22)*100 -> 66.820939 | N22: =K22/(J22+K22)*100 -> 33.179061
I23: Capital Expenditure (Rs. Cr.) | J23: 13696 | K23: 14542 | L23: =J23-K23 -> -846 | M23: =J23/(J23+K23)*100 -> 48.502019 | N23: =K23/(J23+K23)*100 -> 51.497981
I24: Closing Cash (Rs. Cr.) | J24: 8885 | K24: 39256 | L24: =J24-K24 -> -30371 | M24: =J24/(J24+K24)*100 -> 18.456202 | N24: =K24/(J24+K24)*100 -> 81.543798
I25: OCF to Capex Ratio (Times) | J25: =J21/J23 -> 2.5601636 | K25: =K21/K23 -> 1.7296108 | L25: =J25-K25 -> 0.83055277

Sheet Combined & Final Summary
