Workbook

Sheet Instructions
A1: Reusable DCF Financial Modeling Template
A4: Welcome to the Reusable Discounted Cash Flow (DCF) Model!
A5: This Excel sheet is built dynamically using formulas to value any operating company.
A7: Color Coding Guide:
A8: Blue Background + Blue Font (e.g. 12.0%) | B8: Inputs / Assumptions: Feel free to change these for your target company.
A9: White Background + Black Font | B9: Calculated Formulas: DO NOT change these, they update automatically.
A11: Step-by-Step Instructions:
A12: 1. Open the 'DCF Model' tab.
A13: 2. Fill in the 'Historical Financials' section (Columns B to F) with the company's past 5 years of data.
A14: 3. Go to the 'Valuation Drivers & Assumptions' section on the left and set your forecasts (growth, margins, WACC).
A15: 4. Enter the company's current Cash, Debt, Shares Outstanding, and current Market Price.
A16: 5. Check the 'Valuation Metrics' at the top left to see the implied fair share price and upside potential.
A17: 6. Inspect the 'Sensitivity Matrix' to see how WACC and Terminal Growth Rate changes impact the valuation.
A23: SECTION 4: SENSITIVITY MATRIX (IMPLIED SHARE PRICE)
F24: Terminal Growth Rate (g)
E25: WACC / g | F25: 0.03 | G25: 0.035 | H25: 0.04 | I25: 0.045 | J25: 0.05
E26: 0.095 | F26: =((('DCF Model'!G$27/(1+$E26)^1) + ('DCF Model'!H$27/(1+$E26)^2) + ('DCF Model'!I$27/(1+$E26)^3) + ('DCF Model'!J$27/(1+$E26)^4) + ('DCF Model'!K$27/(1+$E26)^5) + ((('DCF Model'!K$27*(1+F$25))/($E26-F$25))/(1+$E26)^5) + 'DCF Model'!$B$11 - 'DCF Model'!$B$12) / 'DCF Model'!$B$13) -> 753.29216 | G26: =((('DCF Model'!G$27/(1+$E26)^1) + ('DCF Model'!H$27/(1+$E26)^2) + ('DCF Model'!I$27/(1+$E26)^3) + ('DCF Model'!J$27/(1+$E26)^4) + ('DCF Model'!K$27/(1+$E26)^5) + ((('DCF Model'!K$27*(1+G$25))/($E26-G$25))/(1+$E26)^5) + 'DCF Model'!$B$11 - 'DCF Model'!$B$12) / 'DCF Model'!$B$13) -> 807.41754 | H26: =((('DCF Model'!G$27/(1+$E26)^1) + ('DCF Model'!H$27/(1+$E26)^2) + ('DCF Model'!I$27/(1+$E26)^3) + ('DCF Model'!J$27/(1+$E26)^4) + ('DCF Model'!K$27/(1+$E26)^5) + ((('DCF Model'!K$27*(1+H$25))/($E26-H$25))/(1+$E26)^5) + 'DCF Model'!$B$11 - 'DCF Model'!$B$12) / 'DCF Model'!$B$13) -> 871.38389 | I26: =((('DCF Model'!G$27/(1+$E26)^1) + ('DCF Model'!H$27/(1+$E26)^2) + ('DCF Model'!I$27/(1+$E26)^3) + ('DCF Model'!J$27/(1+$E26)^4) + ('DCF Model'!K$27/(1+$E26)^5) + ((('DCF Model'!K$27*(1+I$25))/($E26-I$25))/(1+$E26)^5) + 'DCF Model'!$B$11 - 'DCF Model'!$B$12) / 'DCF Model'!$B$13) -> 948.14351 | J26: =((('DCF Model'!G$27/(1+$E26)^1) + ('DCF Model'!H$27/(1+$E26)^2) + ('DCF Model'!I$27/(1+$E26)^3) + ('DCF Model'!J$27/(1+$E26)^4) + ('DCF Model'!K$27/(1+$E26)^5) + ((('DCF Model'!K$27*(1+J$25))/($E26-J$25))/(1+$E26)^5) + 'DCF Model'!$B$11 - 'DCF Model'!$B$12) / 'DCF Model'!$B$13) -> 1041.9608
E27: 0.105 | F27: =((('DCF Model'!G$27/(1+$E27)^1) + ('DCF Model'!H$27/(1+$E27)^2) + ('DCF Model'!I$27/(1+$E27)^3) + ('DCF Model'!J$27/(1+$E27)^4) + ('DCF Model'!K$27/(1+$E27)^5) + ((('DCF Model'!K$27*(1+F$25))/($E27-F$25))/(1+$E27)^5) + 'DCF Model'!$B$11 - 'DCF Model'!$B$12) / 'DCF Model'!$B$13) -> 643.39778 | G27: =((('DCF Model'!G$27/(1+$E27)^1) + ('DCF Model'!H$27/(1+$E27)^2) + ('DCF Model'!I$27/(1+$E27)^3) + ('DCF Model'!J$27/(1+$E27)^4) + ('DCF Model'!K$27/(1+$E27)^5) + ((('DCF Model'!K$27*(1+G$25))/($E27-G$25))/(1+$E27)^5) + 'DCF Model'!$B$11 - 'DCF Model'!$B$12) / 'DCF Model'!$B$13) -> 682.16937 | H27: =((('DCF Model'!G$27/(1+$E27)^1) + ('DCF Model'!H$27/(1+$E27)^2) + ('DCF Model'!I$27/(1+$E27)^3) + ('DCF Model'!J$27/(1+$E27)^4) + ('DCF Model'!K$27/(1+$E27)^5) + ((('DCF Model'!K$27*(1+H$25))/($E27-H$25))/(1+$E27)^5) + 'DCF Model'!$B$11 - 'DCF Model'!$B$12) / 'DCF Model'!$B$13) -> 726.90581 | I27: =((('DCF Model'!G$27/(1+$E27)^1) + ('DCF Model'!H$27/(1+$E27)^2) + ('DCF Model'!I$27/(1+$E27)^3) + ('DCF Model'!J$27/(1+$E27)^4) + ('DCF Model'!K$27/(1+$E27)^5) + ((('DCF Model'!K$27*(1+I$25))/($E27-I$25))/(1+$E27)^5) + 'DCF Model'!$B$11 - 'DCF Model'!$B$12) / 'DCF Model'!$B$13) -> 779.09834 | J27: =((('DCF Model'!G$27/(1+$E27)^1) + ('DCF Model'!H$27/(1+$E27)^2) + ('DCF Model'!I$27/(1+$E27)^3) + ('DCF Model'!J$27/(1+$E27)^4) + ('DCF Model'!K$27/(1+$E27)^5) + ((('DCF Model'!K$27*(1+J$25))/($E27-J$25))/(1+$E27)^5) + 'DCF Model'!$B$11 - 'DCF Model'!$B$12) / 'DCF Model'!$B$13) -> 840.78041
E28: 0.115 | F28: =((('DCF Model'!G$27/(1+$E28)^1) + ('DCF Model'!H$27/(1+$E28)^2) + ('DCF Model'!I$27/(1+$E28)^3) + ('DCF Model'!J$27/(1+$E28)^4) + ('DCF Model'!K$27/(1+$E28)^5) + ((('DCF Model'!K$27*(1+F$25))/($E28-F$25))/(1+$E28)^5) + 'DCF Model'!$B$11 - 'DCF Model'!$B$12) / 'DCF Model'!$B$13) -> 559.50888 | G28: =((('DCF Model'!G$27/(1+$E28)^1) + ('DCF Model'!H$27/(1+$E28)^2) + ('DCF Model'!I$27/(1+$E28)^3) + ('DCF Model'!J$27/(1+$E28)^4) + ('DCF Model'!K$27/(1+$E28)^5) + ((('DCF Model'!K$27*(1+G$25))/($E28-G$25))/(1+$E28)^5) + 'DCF Model'!$B$11 - 'DCF Model'!$B$12) / 'DCF Model'!$B$13) -> 588.38332 | H28: =((('DCF Model'!G$27/(1+$E28)^1) + ('DCF Model'!H$27/(1+$E28)^2) + ('DCF Model'!I$27/(1+$E28)^3) + ('DCF Model'!J$27/(1+$E28)^4) + ('DCF Model'!K$27/(1+$E28)^5) + ((('DCF Model'!K$27*(1+H$25))/($E28-H$25))/(1+$E28)^5) + 'DCF Model'!$B$11 - 'DCF Model'!$B$12) / 'DCF Model'!$B$13) -> 621.10769 | I28: =((('DCF Model'!G$27/(1+$E28)^1) + ('DCF Model'!H$27/(1+$E28)^2) + ('DCF Model'!I$27/(1+$E28)^3) + ('DCF Model'!J$27/(1+$E28)^4) + ('DCF Model'!K$27/(1+$E28)^5) + ((('DCF Model'!K$27*(1+I$25))/($E28-I$25))/(1+$E28)^5) + 'DCF Model'!$B$11 - 'DCF Model'!$B$12) / 'DCF Model'!$B$13) -> 658.50697 | J28: =((('DCF Model'!G$27/(1+$E28)^1) + ('DCF Model'!H$27/(1+$E28)^2) + ('DCF Model'!I$27/(1+$E28)^3) + ('DCF Model'!J$27/(1+$E28)^4) + ('DCF Model'!K$27/(1+$E28)^5) + ((('DCF Model'!K$27*(1+J$25))/($E28-J$25))/(1+$E28)^5) + 'DCF Model'!$B$11 - 'DCF Model'!$B$12) / 'DCF Model'!$B$13) -> 701.65998
E29: 0.125 | F29: =((('DCF Model'!G$27/(1+$E29)^1) + ('DCF Model'!H$27/(1+$E29)^2) + ('DCF Model'!I$27/(1+$E29)^3) + ('DCF Model'!J$27/(1+$E29)^4) + ('DCF Model'!K$27/(1+$E29)^5) + ((('DCF Model'!K$27*(1+F$25))/($E29-F$25))/(1+$E29)^5) + 'DCF Model'!$B$11 - 'DCF Model'!$B$12) / 'DCF Model'!$B$13) -> 493.40707 | G29: =((('DCF Model'!G$27/(1+$E29)^1) + ('DCF Model'!H$27/(1+$E29)^2) + ('DCF Model'!I$27/(1+$E29)^3) + ('DCF Model'!J$27/(1+$E29)^4) + ('DCF Model'!K$27/(1+$E29)^5) + ((('DCF Model'!K$27*(1+G$25))/($E29-G$25))/(1+$E29)^5) + 'DCF Model'!$B$11 - 'DCF Model'!$B$12) / 'DCF Model'!$B$13) -> 515.56585 | H29: =((('DCF Model'!G$27/(1+$E29)^1) + ('DCF Model'!H$27/(1+$E29)^2) + ('DCF Model'!I$27/(1+$E29)^3) + ('DCF Model'!J$27/(1+$E29)^4) + ('DCF Model'!K$27/(1+$E29)^5) + ((('DCF Model'!K$27*(1+H$25))/($E29-H$25))/(1+$E29)^5) + 'DCF Model'!$B$11 - 'DCF Model'!$B$12) / 'DCF Model'!$B$13) -> 540.33154 | I29: =((('DCF Model'!G$27/(1+$E29)^1) + ('DCF Model'!H$27/(1+$E29)^2) + ('DCF Model'!I$27/(1+$E29)^3) + ('DCF Model'!J$27/(1+$E29)^4) + ('DCF Model'!K$27/(1+$E29)^5) + ((('DCF Model'!K$27*(1+I$25))/($E29-I$25))/(1+$E29)^5) + 'DCF Model'!$B$11 - 'DCF Model'!$B$12) / 'DCF Model'!$B$13) -> 568.19294 | J29: =((('DCF Model'!G$27/(1+$E29)^1) + ('DCF Model'!H$27/(1+$E29)^2) + ('DCF Model'!I$27/(1+$E29)^3) + ('DCF Model'!J$27/(1+$E29)^4) + ('DCF Model'!K$27/(1+$E29)^5) + ((('DCF Model'!K$27*(1+J$25))/($E29-J$25))/(1+$E29)^5) + 'DCF Model'!$B$11 - 'DCF Model'!$B$12) / 'DCF Model'!$B$13) -> 599.7692
E30: 0.135 | F30: =((('DCF Model'!G$27/(1+$E30)^1) + ('DCF Model'!H$27/(1+$E30)^2) + ('DCF Model'!I$27/(1+$E30)^3) + ('DCF Model'!J$27/(1+$E30)^4) + ('DCF Model'!K$27/(1+$E30)^5) + ((('DCF Model'!K$27*(1+F$25))/($E30-F$25))/(1+$E30)^5) + 'DCF Model'!$B$11 - 'DCF Model'!$B$12) / 'DCF Model'!$B$13) -> 440.00507 | G30: =((('DCF Model'!G$27/(1+$E30)^1) + ('DCF Model'!H$27/(1+$E30)^2) + ('DCF Model'!I$27/(1+$E30)^3) + ('DCF Model'!J$27/(1+$E30)^4) + ('DCF Model'!K$27/(1+$E30)^5) + ((('DCF Model'!K$27*(1+G$25))/($E30-G$25))/(1+$E30)^5) + 'DCF Model'!$B$11 - 'DCF Model'!$B$12) / 'DCF Model'!$B$13) -> 457.42111 | H30: =((('DCF Model'!G$27/(1+$E30)^1) + ('DCF Model'!H$27/(1+$E30)^2) + ('DCF Model'!I$27/(1+$E30)^3) + ('DCF Model'!J$27/(1+$E30)^4) + ('DCF Model'!K$27/(1+$E30)^5) + ((('DCF Model'!K$27*(1+H$25))/($E30-H$25))/(1+$E30)^5) + 'DCF Model'!$B$11 - 'DCF Model'!$B$12) / 'DCF Model'!$B$13) -> 476.67041 | I30: =((('DCF Model'!G$27/(1+$E30)^1) + ('DCF Model'!H$27/(1+$E30)^2) + ('DCF Model'!I$27/(1+$E30)^3) + ('DCF Model'!J$27/(1+$E30)^4) + ('DCF Model'!K$27/(1+$E30)^5) + ((('DCF Model'!K$27*(1+I$25))/($E30-I$25))/(1+$E30)^5) + 'DCF Model'!$B$11 - 'DCF Model'!$B$12) / 'DCF Model'!$B$13) -> 498.05852 | J30: =((('DCF Model'!G$27/(1+$E30)^1) + ('DCF Model'!H$27/(1+$E30)^2) + ('DCF Model'!I$27/(1+$E30)^3) + ('DCF Model'!J$27/(1+$E30)^4) + ('DCF Model'!K$27/(1+$E30)^5) + ((('DCF Model'!K$27*(1+J$25))/($E30-J$25))/(1+$E30)^5) + 'DCF Model'!$B$11 - 'DCF Model'!$B$12) / 'DCF Model'!$B$13) -> 521.96288

Sheet DCF Model
A1: DISCOUNTED CASH FLOW (DCF) VALUATION MODEL
A3: SECTION 1: VALUATION DRIVERS & ASSUMPTIONS
A4: Revenue Forecast Period Growth Rate | B4: 0.14 | C4: Percentage growth for FY27E-FY31E | F4: (14.6%) is the 5-year average but we deliberately chose a lower number (14%) to be safe and conservative.
A5: EBITDA Margin Assumption | B5: 0.135 | C5: Operating profit margin
A6: CapEx as % of Revenue | B6: 0.02 | C6: Expected capital expenditure intensity
A7: Net Working Capital change % of Rev | B7: 0.015 | C7: Expected operational working capital cycle
A8: Weighted Average Cost of Capital (WACC) | B8: 0.115 | C8: Required rate of return (Discount Rate)
A9: Terminal Growth Rate (g) | B9: 0.04 | C9: Stable growth rate to infinity
A10: Effective Tax Rate | B10: 0.25 | C10: Corporate income tax rate
A11: Cash and Equivalents (Cr) | B11: 52.8 | C11: Non-operating cash from latest balance sheet
A12: Total Debt (Cr) | B12: 531.3 | C12: Total borrowings from latest balance sheet
A13: Shares Outstanding (Cr) | B13: 13.365 | C13: Total number of common shares outstanding
A14: Current Market Share Price | B14: 426 | C14: Latest closing stock price
A16: SECTION 2: 5-YEAR HISTORICALS & 5-YEAR PROJECTIONS
A17: Line Item | B17: FY22A | C17: FY23A | D17: FY24A | E17: FY25A | F17: FY26A | G17: FY27E | H17: FY28E | I17: FY29E | J17: FY30E | K17: FY31E
A18: Revenue from Operations | B18: 3056.04 | C18: 4421.08 | D18: 4259.12 | E18: 4619.84 | F18: 5266.19 | G18: =F18*(1+$B$4) -> 6003.4566 | H18: =G18*(1+$B$4) -> 6843.9405 | I18: =H18*(1+$B$4) -> 7802.0922 | J18: =I18*(1+$B$4) -> 8894.3851 | K18: =J18*(1+$B$4) -> 10139.599
A19: EBITDA | B19: 180.16 | C19: 452.64 | D19: 510.53 | E19: 602 | F19: 704.56 | G19: =G18*$B$5 -> 810.46664 | H19: =H18*$B$5 -> 923.93197 | I19: =I18*$B$5 -> 1053.2824 | J19: =J18*$B$5 -> 1200.742 | K19: =K18*$B$5 -> 1368.8459
A20: Less: Depreciation & Amortisation | B20: 233 | C20: 238.73 | D20: 230.08 | E20: 255.72 | F20: 289.68 | G20: =F20*(1+$B$4) -> 330.2352 | H20: =G20*(1+$B$4) -> 376.46813 | I20: =H20*(1+$B$4) -> 429.17367 | J20: =I20*(1+$B$4) -> 489.25798 | K20: =J20*(1+$B$4) -> 557.7541
A21: Operating Profit (EBIT) | B21: =B19-B20 -> -52.84 | C21: =C19-C20 -> 213.91 | D21: =D19-D20 -> 280.45 | E21: =E19-E20 -> 346.28 | F21: =F19-F20 -> 414.88 | G21: =G19-G20 -> 480.23144 | H21: =H19-H20 -> 547.46384 | I21: =I19-I20 -> 624.10878 | ... K21: =K19-K20 -> 811.09177
A22: Less: Taxes | B22: =MAX(0, B21*$B$10) -> 0 | C22: =MAX(0, C21*$B$10) -> 53.4775 | D22: =MAX(0, D21*$B$10) -> 70.1125 | E22: =MAX(0, E21*$B$10) -> 86.57 | F22: =MAX(0, F21*$B$10) -> 103.72 | G22: =MAX(0, G21*$B$10) -> 120.05786 | H22: =MAX(0, H21*$B$10) -> 136.86596 | I22: =MAX(0, I21*$B$10) -> 156.0272 | ... K22: =MAX(0, K21*$B$10) -> 202.77294
A23: Net Operating Profit Less Taxes (NOPAT) | B23: =B21-B22 -> -52.84 | C23: =C21-C22 -> 160.4325 | D23: =D21-D22 -> 210.3375 | E23: =E21-E22 -> 259.71 | F23: =F21-F22 -> 311.16 | G23: =G21-G22 -> 360.17358 | H23: =H21-H22 -> 410.59788 | I23: =I21-I22 -> 468.08159 | ... K23: =K21-K22 -> 608.31883
A24: Plus: Depreciation & Amortisation | B24: =B20 -> 233 | C24: =C20 -> 238.73 | D24: =D20 -> 230.08 | E24: =E20 -> 255.72 | F24: =F20 -> 289.68 | G24: =G20 -> 330.2352 | H24: =H20 -> 376.46813 | I24: =I20 -> 429.17367 | ... K24: =K20 -> 557.7541
A25: Less: Capital Expenditures (CapEx) | B25: 16.6 | C25: -63.24 | D25: -82.27 | E25: -95.82 | F25: -108.95 | G25: =G18*$B$6 -> 120.06913 | H25: =H18*$B$6 -> 136.87881 | I25: =I18*$B$6 -> 156.04184 | J25: =J18*$B$6 -> 177.8877 | K25: =K18*$B$6 -> 202.79198
A26: Less: Change in Working Capital | B26: 278.15 | C26: -95.52 | D26: -3.1 | E26: -61.33 | F26: -258.77 | G26: =G18*$B$7 -> 90.051849 | H26: =H18*$B$7 -> 102.65911 | I26: =I18*$B$7 -> 117.03138 | J26: =J18*$B$7 -> 133.41578 | K26: =K18*$B$7 -> 152.09399
A27: Free Cash Flow to Firm (FCFF) | G27: =G23+G24-G25-G26 -> 480.2878 | H27: =H23+H24-H25-H26 -> 547.52809 | I27: =I23+I24-I25-I26 -> 624.18202 | J27: =J23+J24-J25-J26 -> 711.56751 | K27: =K23+K24-K25-K26 -> 811.18696
A28: Discount Factor | G28: =1/(1+$B$8)^1 -> 0.89686099 | H28: =1/(1+$B$8)^2 -> 0.80435963 | I28: =1/(1+$B$8)^3 -> 0.72139877 | J28: =1/(1+$B$8)^4 -> 0.64699441 | K28: =1/(1+$B$8)^5 -> 0.58026405
A29: Present Value of FCFF | G29: =G27*G28 -> 430.75139 | H29: =H27*H28 -> 440.40949 | I29: =I27*I28 -> 450.28415 | J29: =J27*J28 -> 460.3802 | K29: =K27*K28 -> 470.70263
A31: SECTION 3: VALUATION BRIDGE
A32: Sum of PV of explicit Cash Flows | B32: =SUM(G29:K29) -> 2252.5279 | C32: Cumulative discounted FCFF
A33: Terminal Value (Gordon Growth) | B33: =(K27*(1+$B$9))/($B$8-$B$9) -> 11248.459 | C33: Valuation beyond forecast horizon
A34: PV of Terminal Value | B34: =B33*K28 -> 6527.0764 | C34: Discounted Terminal Value to today
A35: Enterprise Value (EV) | B35: =B32+B34 -> 8779.6043 | C35: Sum of explicit and terminal PVs
A36: Plus: Cash and Equivalents | B36: =B11 -> 52.8 | C36: Non-operating liquidity
A37: Less: Total Debt | B37: =B12 -> 531.3 | C37: All interest-bearing debt
A38: Equity Value | B38: =B35+B36-B37 -> 8301.1043 | C38: Enterprise Value + Cash - Debt
A39: Shares Outstanding (Cr) | B39: =B13 -> 13.365 | C39: Common shares outstanding
A40: Implied Share Price (₹) | B40: =B38/B39 -> 621.10769 | C40: Calculated fair value per share
A41: Current Market Price (₹) | B41: =B14 -> 426 | C41: Current market pricing
A42: Implied Premium / (Discount) | B42: =(B40/B41)-1 -> 0.45799928 | C42: Upside potential to current price

Sheet Assumption_Calculations
A1: Factor / Assumption | B1: Value in Model | C1: The Math (How it was calculated) | D1: Layman Explanation (What it means)
A2: Revenue Forecast Growth Rate | B2: =(('DCF Model'!F18/'DCF Model'!B18)^(1/4))-1 -> 0.14573551 | C2: (FY26 Rev / FY22 Rev)^1/n - 1 (5,266 / 3056.04)^1/4 - 1 = 14.0% | D2: Did it in a way like CAGR is calculated.
A3: EBITDA Margin Assumption | B3: 13.5% | C3: FY26 EBITDA / FY26 Revenue (704.56 / 5,266.19) = 13.4%, slightly bumped to 13.5% | D3: Based on Historic trend and growth assuming the 5th year rate.
A4: CapEx as % of Revenue | B4: 2.0% | C4: Average of FY25 & FY26 CapEx divided by Revenue Capital Expenditure ÷ Revenue | D4: FY22: 0.5% (CapEx: ₹16.6 Cr) FY23: 1.4% (CapEx: ₹63.2 Cr) FY24: 1.9% (CapEx: ₹82.2 Cr) FY25: 2.1% (CapEx: ₹95.8 Cr) FY26: 2.1% (CapEx: ₹108.9 Cr) so taken average of 2%
A5: Net Working Capital change % | B5: 1.5% | C5: Historical average of NWC changes as a % of Revenue | D5: This is the cash trapped in day-to-day operations (like unsold clothes in inventory). We use an average to smooth out bumps.
A6: Weighted Average Cost of Capital (WACC) | B6: 11.5% | C6: Cost of Equity × Equity% + Cost of Debt × Debt% × (1 - Tax) | D6: We use 11.5% as a standard, fair rate for Indian retail companies of this size.
A7: Terminal Growth Rate (g) | B7: 4.0% | C7: Anchored to India's long-term inflation target (4%) | D7: We can't forecast forever. So after 5 years, we assume the company just grows steadily at the same speed as the overall economy (inflation).
A8: Effective Tax Rate | B8: 25.0% | C8: Statutory Indian Corporate Tax Rate | D8: The standard baseline tax rate set by the Government of India for corporations.
A9: Cash and Equivalents | B9: ₹52.80 Cr | C9: Exact figure from the latest FY26 Balance Sheet | D9: The actual money sitting in their bank accounts right now.
A10: Total Debt | B10: ₹531.30 Cr | C10: Exact figure from the latest FY26 Balance Sheet | D10: The total loans they owe to banks right now.
A11: Shares Outstanding | B11: 13.37 Cr | C11: Total Equity Capital (53.46) / Face Value per share (4) | D11: ₹53.46 Cr equity capital and ₹4 face value belong to Arvind Fashions ltd.
A12: Current Market Share Price | B12: 426 | C12: Latest closing price from the Stock Exchange (NSE/BSE) | D12: What one slice of the pie costs to buy on the stock market today. | E12: 46283
